[
  {
    "shelf": "Étagère Principale",
    "title": "À propos des manuscrits",
    "created": "2021-09-30 19:56",
    "updated": "2021-09-30 19:56",
    "pages": [
      {
        "num": "5",
        "w": "297",
        "h": "210",
        "unit": "mm",
        "content": [
          { "type": "script",  "x":  "55.8", "y": "26.3", "s": "0", "text": "" },
          { "type": "anchor",  "x":  "55.8", "y": "26.3", "id": "" },
          { "type": "runes",   "x":  "15.7", "y": "52.9", "text": "11213"  },
          { "type": "link",    "x": "118.0", "y": "52.9", "s": "3", "id": "", "text": "" },
          { "type": "drawing", "x":  "15.7", "y": "83.0", "strokes": [
            { "type": "open", "s": ".5", "path": "M 0 0 l 2 3 m 4 4 c -2 -2, 4 -6, 6 -6" },
            { "type": "close", "path": "M 6 0 c 0 -.552, .448 -1, 1 -1, .552 0, 1 .448, 1 1, 0 .552, -.448 1, -1 1, -.552 0, -1 -.448, -1 -1" },
            { "type": "fill", "path": "M 10 -2 c 0 -.552, .448 -1, 1 -1, .552 0, 1 .448, 1 1, 0 .552, -.448 1, -1 1, -.552 0, -1 -.448, -1 -1" },
            { "type": "open", "path": "M 12 12 c 0.214,-0.027 0.200,0.282 0.123,0.395 -0.197,0.287 -0.620,0.212 -0.836,-0.008 -0.359,-0.369 -0.233,-0.969 0.139,-1.276 0.530,-0.438 1.32,-0.255 1.717,0.270 0.519,0.689 0.279,1.675 -0.401,2.158 -0.846,0.600 -2.030,0.302 -2.599,-0.532 -0.684,-1.003 -0.327,-2.385 0.663,-3.039 1.152,-0.762 2.722,-0.357 3.467,0.774" }
          ]},
          { "type": "script",  "x":  "55.8", "y": "100", "s": "1", "text": "" },
          { "type": "script",  "x":  "55.8", "y": "118", "s": "2", "text": "" },
          { "type": "script",  "x":  "55.8", "y": "136", "s": "3", "text": "" }
        ]
      }
    ]
  }
]
